__init__.py
mongodb_atlas_data_api.py
mongodb_atlas_data_api-0.0.4.dist-info/LICENSE
mongodb_atlas_data_api-0.0.4.dist-info/METADATA
mongodb_atlas_data_api-0.0.4.dist-info/WHEEL
mongodb_atlas_data_api-0.0.4.dist-info/top_level.txt
mongodb_atlas_data_api-0.0.4.dist-info/RECORD
