Metadata-Version: 2.1
Name: mongodb-atlas-data-api
Version: 0.0.4
Summary: A simple Python Integration with the MongoDB Atlas Data API. It's useful in certain scenarios.
Author-email: Carlos Guerrero <imcarlosguerrero@gmail.com>
License: MIT License
Project-URL: Homepage, https://github.com/imcarlosguerrero/mongodb-atlas-data-api
Keywords: mongodb,mongodb atlas,mongodb data api
Classifier: License :: OSI Approved :: MIT License
Classifier: Programming Language :: Python
Classifier: Programming Language :: Python :: 3
Requires-Python: >=3.6
License-File: LICENSE
Requires-Dist: requests
